[
  {
    "id": 545061,
    "hour_dk": "2025-10-10T00:00:00.000000Z",
    "hour_utc": "2025-10-09T22:00:00.000000Z",
    "price_zone": "DK2",
    "price_dkk": 407.6825,
    "price_eur": 54.6,
    "created_at": "2025-10-09T11:10:04.000000Z",
    "updated_at": "2025-10-09T21:20:05.000000Z"
  },
  {
    "id": 545069,
    "hour_dk": "2025-10-10T01:00:00.000000Z",
    "hour_utc": "2025-10-09T23:00:00.000000Z",
    "price_zone": "DK2",
    "price_dkk": 340.72499999999997,
    "price_eur": 45.6325,
    "created_at": "2025-10-09T11:10:04.000000Z",
    "updated_at": "2025-10-09T21:20:05.000000Z"
  },
  {
    "id": 545077,
    "hour_dk": "2025-10-10T02:00:00.000000Z",
    "hour_utc": "2025-10-10T00:00:00.000000Z",
    "price_zone": "DK2",
    "price_dkk": 364.115,
    "price_eur": 48.765,
    "created_at": "2025-10-09T11:10:04.000000Z",
    "updated_at": "2025-10-09T21:20:05.000000Z"
  },
  {
    "id": 545085,
    "hour_dk": "2025-10-10T03:00:00.000000Z",
    "hour_utc": "2025-10-10T01:00:00.000000Z",
    "price_zone": "DK2",
    "price_dkk": 334.2275000000001,
    "price_eur": 44.7625,
    "created_at": "2025-10-09T11:10:04.000000Z",
    "updated_at": "2025-10-09T21:20:05.000000Z"
  },
  {
    "id": 545093,
    "hour_dk": "2025-10-10T04:00:00.000000Z",
    "hour_utc": "2025-10-10T02:00:00.000000Z",
    "price_zone": "DK2",
    "price_dkk": 312.37,
    "price_eur": 41.835,
    "created_at": "2025-10-09T11:10:04.000000Z",
    "updated_at": "2025-10-09T21:20:05.000000Z"
  },
  {
    "id": 545101,
    "hour_dk": "2025-10-10T05:00:00.000000Z",
    "hour_utc": "2025-10-10T03:00:00.000000Z",
    "price_zone": "DK2",
    "price_dkk": 331.8775,
    "price_eur": 44.4475,
    "created_at": "2025-10-09T11:10:04.000000Z",
    "updated_at": "2025-10-09T21:20:05.000000Z"
  },
  {
    "id": 545109,
    "hour_dk": "2025-10-10T06:00:00.000000Z",
    "hour_utc": "2025-10-10T04:00:00.000000Z",
    "price_zone": "DK2",
    "price_dkk": 512.5325,
    "price_eur": 68.6425,
    "created_at": "2025-10-09T11:10:04.000000Z",
    "updated_at": "2025-10-09T21:20:05.000000Z"
  },
  {
    "id": 545117,
    "hour_dk": "2025-10-10T07:00:00.000000Z",
    "hour_utc": "2025-10-10T05:00:00.000000Z",
    "price_zone": "DK2",
    "price_dkk": 663.7325,
    "price_eur": 88.89250000000001,
    "created_at": "2025-10-09T11:10:04.000000Z",
    "updated_at": "2025-10-09T21:20:05.000000Z"
  },
  {
    "id": 545125,
    "hour_dk": "2025-10-10T08:00:00.000000Z",
    "hour_utc": "2025-10-10T06:00:00.000000Z",
    "price_zone": "DK2",
    "price_dkk": 709.4125,
    "price_eur": 95.00999999999999,
    "created_at": "2025-10-09T11:10:04.000000Z",
    "updated_at": "2025-10-09T21:20:05.000000Z"
  },
  {
    "id": 545133,
    "hour_dk": "2025-10-10T09:00:00.000000Z",
    "hour_utc": "2025-10-10T07:00:00.000000Z",
    "price_zone": "DK2",
    "price_dkk": 559.03,
    "price_eur": 74.87,
    "created_at": "2025-10-09T11:10:04.000000Z",
    "updated_at": "2025-10-09T21:20:05.000000Z"
  },
  {
    "id": 545141,
    "hour_dk": "2025-10-10T10:00:00.000000Z",
    "hour_utc": "2025-10-10T08:00:00.000000Z",
    "price_zone": "DK2",
    "price_dkk": 482.87,
    "price_eur": 64.66999999999999,
    "created_at": "2025-10-09T11:10:04.000000Z",
    "updated_at": "2025-10-09T21:20:05.000000Z"
  },
  {
    "id": 545149,
    "hour_dk": "2025-10-10T11:00:00.000000Z",
    "hour_utc": "2025-10-10T09:00:00.000000Z",
    "price_zone": "DK2",
    "price_dkk": 436.91499999999996,
    "price_eur": 58.515,
    "created_at": "2025-10-09T11:10:04.000000Z",
    "updated_at": "2025-10-09T21:20:05.000000Z"
  },
  {
    "id": 545157,
    "hour_dk": "2025-10-10T12:00:00.000000Z",
    "hour_utc": "2025-10-10T10:00:00.000000Z",
    "price_zone": "DK2",
    "price_dkk": 402.88250000000005,
    "price_eur": 53.957499999999996,
    "created_at": "2025-10-09T11:10:04.000000Z",
    "updated_at": "2025-10-09T21:20:05.000000Z"
  },
  {
    "id": 545165,
    "hour_dk": "2025-10-10T13:00:00.000000Z",
    "hour_utc": "2025-10-10T11:00:00.000000Z",
    "price_zone": "DK2",
    "price_dkk": 393.79499999999996,
    "price_eur": 52.739999999999995,
    "created_at": "2025-10-09T11:10:04.000000Z",
    "updated_at": "2025-10-09T21:20:05.000000Z"
  },
  {
    "id": 545173,
    "hour_dk": "2025-10-10T14:00:00.000000Z",
    "hour_utc": "2025-10-10T12:00:00.000000Z",
    "price_zone": "DK2",
    "price_dkk": 374.38,
    "price_eur": 50.14,
    "created_at": "2025-10-09T11:10:04.000000Z",
    "updated_at": "2025-10-09T21:20:05.000000Z"
  },
  {
    "id": 545181,
    "hour_dk": "2025-10-10T15:00:00.000000Z",
    "hour_utc": "2025-10-10T13:00:00.000000Z",
    "price_zone": "DK2",
    "price_dkk": 369.22999999999996,
    "price_eur": 49.45,
    "created_at": "2025-10-09T11:10:04.000000Z",
    "updated_at": "2025-10-09T21:20:05.000000Z"
  },
  {
    "id": 545189,
    "hour_dk": "2025-10-10T16:00:00.000000Z",
    "hour_utc": "2025-10-10T14:00:00.000000Z",
    "price_zone": "DK2",
    "price_dkk": 440.9075,
    "price_eur": 59.05,
    "created_at": "2025-10-09T11:10:04.000000Z",
    "updated_at": "2025-10-09T21:20:05.000000Z"
  },
  {
    "id": 545197,
    "hour_dk": "2025-10-10T17:00:00.000000Z",
    "hour_utc": "2025-10-10T15:00:00.000000Z",
    "price_zone": "DK2",
    "price_dkk": 564.2375,
    "price_eur": 75.5675,
    "created_at": "2025-10-09T11:10:04.000000Z",
    "updated_at": "2025-10-09T21:20:05.000000Z"
  },
  {
    "id": 545205,
    "hour_dk": "2025-10-10T18:00:00.000000Z",
    "hour_utc": "2025-10-10T16:00:00.000000Z",
    "price_zone": "DK2",
    "price_dkk": 691.715,
    "price_eur": 92.63999999999999,
    "created_at": "2025-10-09T11:10:04.000000Z",
    "updated_at": "2025-10-09T21:20:05.000000Z"
  },
  {
    "id": 545213,
    "hour_dk": "2025-10-10T19:00:00.000000Z",
    "hour_utc": "2025-10-10T17:00:00.000000Z",
    "price_zone": "DK2",
    "price_dkk": 691.94,
    "price_eur": 92.67,
    "created_at": "2025-10-09T11:10:04.000000Z",
    "updated_at": "2025-10-09T21:20:05.000000Z"
  },
  {
    "id": 545221,
    "hour_dk": "2025-10-10T20:00:00.000000Z",
    "hour_utc": "2025-10-10T18:00:00.000000Z",
    "price_zone": "DK2",
    "price_dkk": 557.8025,
    "price_eur": 74.70500000000001,
    "created_at": "2025-10-09T11:10:04.000000Z",
    "updated_at": "2025-10-09T21:20:05.000000Z"
  },
  {
    "id": 545229,
    "hour_dk": "2025-10-10T21:00:00.000000Z",
    "hour_utc": "2025-10-10T19:00:00.000000Z",
    "price_zone": "DK2",
    "price_dkk": 493.3225,
    "price_eur": 66.07000000000001,
    "created_at": "2025-10-09T11:10:04.000000Z",
    "updated_at": "2025-10-09T21:20:05.000000Z"
  },
  {
    "id": 545237,
    "hour_dk": "2025-10-10T22:00:00.000000Z",
    "hour_utc": "2025-10-10T20:00:00.000000Z",
    "price_zone": "DK2",
    "price_dkk": 479.96000000000004,
    "price_eur": 64.28,
    "created_at": "2025-10-09T11:10:04.000000Z",
    "updated_at": "2025-10-09T21:20:05.000000Z"
  },
  {
    "id": 545245,
    "hour_dk": "2025-10-10T23:00:00.000000Z",
    "hour_utc": "2025-10-10T21:00:00.000000Z",
    "price_zone": "DK2",
    "price_dkk": 455.58,
    "price_eur": 61.015,
    "created_at": "2025-10-09T11:10:04.000000Z",
    "updated_at": "2025-10-09T21:20:05.000000Z"
  }
]
