[
  {
    "id": 73780,
    "hour_dk": "2025-09-17T00:00:00.000000Z",
    "hour_utc": "2025-09-16T22:00:00.000000Z",
    "price_zone": "DK2",
    "price_dkk": 497.07,
    "price_eur": 66.59,
    "created_at": "2025-09-16T11:00:05.000000Z",
    "updated_at": "2025-09-16T21:20:04.000000Z"
  },
  {
    "id": 73783,
    "hour_dk": "2025-09-17T01:00:00.000000Z",
    "hour_utc": "2025-09-16T23:00:00.000000Z",
    "price_zone": "DK2",
    "price_dkk": 446.98,
    "price_eur": 59.88,
    "created_at": "2025-09-16T11:00:05.000000Z",
    "updated_at": "2025-09-16T21:20:04.000000Z"
  },
  {
    "id": 73784,
    "hour_dk": "2025-09-17T02:00:00.000000Z",
    "hour_utc": "2025-09-17T00:00:00.000000Z",
    "price_zone": "DK2",
    "price_dkk": 357.85,
    "price_eur": 47.94,
    "created_at": "2025-09-16T11:00:05.000000Z",
    "updated_at": "2025-09-16T21:20:04.000000Z"
  },
  {
    "id": 73787,
    "hour_dk": "2025-09-17T03:00:00.000000Z",
    "hour_utc": "2025-09-17T01:00:00.000000Z",
    "price_zone": "DK2",
    "price_dkk": 340.24,
    "price_eur": 45.58,
    "created_at": "2025-09-16T11:00:05.000000Z",
    "updated_at": "2025-09-16T21:20:04.000000Z"
  },
  {
    "id": 73788,
    "hour_dk": "2025-09-17T04:00:00.000000Z",
    "hour_utc": "2025-09-17T02:00:00.000000Z",
    "price_zone": "DK2",
    "price_dkk": 380.69,
    "price_eur": 51,
    "created_at": "2025-09-16T11:00:06.000000Z",
    "updated_at": "2025-09-16T21:20:04.000000Z"
  },
  {
    "id": 73791,
    "hour_dk": "2025-09-17T05:00:00.000000Z",
    "hour_utc": "2025-09-17T03:00:00.000000Z",
    "price_zone": "DK2",
    "price_dkk": 516.85,
    "price_eur": 69.24,
    "created_at": "2025-09-16T11:00:06.000000Z",
    "updated_at": "2025-09-16T21:20:04.000000Z"
  },
  {
    "id": 73792,
    "hour_dk": "2025-09-17T06:00:00.000000Z",
    "hour_utc": "2025-09-17T04:00:00.000000Z",
    "price_zone": "DK2",
    "price_dkk": 694.51,
    "price_eur": 93.04,
    "created_at": "2025-09-16T11:00:06.000000Z",
    "updated_at": "2025-09-16T21:20:04.000000Z"
  },
  {
    "id": 73795,
    "hour_dk": "2025-09-17T07:00:00.000000Z",
    "hour_utc": "2025-09-17T05:00:00.000000Z",
    "price_zone": "DK2",
    "price_dkk": 836.93,
    "price_eur": 112.12,
    "created_at": "2025-09-16T11:00:06.000000Z",
    "updated_at": "2025-09-16T21:20:05.000000Z"
  },
  {
    "id": 73796,
    "hour_dk": "2025-09-17T08:00:00.000000Z",
    "hour_utc": "2025-09-17T06:00:00.000000Z",
    "price_zone": "DK2",
    "price_dkk": 815.58,
    "price_eur": 109.26,
    "created_at": "2025-09-16T11:00:06.000000Z",
    "updated_at": "2025-09-16T21:20:05.000000Z"
  },
  {
    "id": 73799,
    "hour_dk": "2025-09-17T09:00:00.000000Z",
    "hour_utc": "2025-09-17T07:00:00.000000Z",
    "price_zone": "DK2",
    "price_dkk": 671.81,
    "price_eur": 90,
    "created_at": "2025-09-16T11:00:06.000000Z",
    "updated_at": "2025-09-16T21:20:05.000000Z"
  },
  {
    "id": 73800,
    "hour_dk": "2025-09-17T10:00:00.000000Z",
    "hour_utc": "2025-09-17T08:00:00.000000Z",
    "price_zone": "DK2",
    "price_dkk": 478.63,
    "price_eur": 64.12,
    "created_at": "2025-09-16T11:00:06.000000Z",
    "updated_at": "2025-09-16T21:20:05.000000Z"
  },
  {
    "id": 73803,
    "hour_dk": "2025-09-17T11:00:00.000000Z",
    "hour_utc": "2025-09-17T09:00:00.000000Z",
    "price_zone": "DK2",
    "price_dkk": 30.46,
    "price_eur": 4.08,
    "created_at": "2025-09-16T11:00:06.000000Z",
    "updated_at": "2025-09-16T21:20:05.000000Z"
  },
  {
    "id": 73804,
    "hour_dk": "2025-09-17T12:00:00.000000Z",
    "hour_utc": "2025-09-17T10:00:00.000000Z",
    "price_zone": "DK2",
    "price_dkk": 30.31,
    "price_eur": 4.06,
    "created_at": "2025-09-16T11:00:06.000000Z",
    "updated_at": "2025-09-16T21:20:05.000000Z"
  },
  {
    "id": 73807,
    "hour_dk": "2025-09-17T13:00:00.000000Z",
    "hour_utc": "2025-09-17T11:00:00.000000Z",
    "price_zone": "DK2",
    "price_dkk": 30.08,
    "price_eur": 4.03,
    "created_at": "2025-09-16T11:00:06.000000Z",
    "updated_at": "2025-09-16T21:20:05.000000Z"
  },
  {
    "id": 73808,
    "hour_dk": "2025-09-17T14:00:00.000000Z",
    "hour_utc": "2025-09-17T12:00:00.000000Z",
    "price_zone": "DK2",
    "price_dkk": 30.31,
    "price_eur": 4.06,
    "created_at": "2025-09-16T11:00:06.000000Z",
    "updated_at": "2025-09-16T21:20:05.000000Z"
  },
  {
    "id": 73811,
    "hour_dk": "2025-09-17T15:00:00.000000Z",
    "hour_utc": "2025-09-17T13:00:00.000000Z",
    "price_zone": "DK2",
    "price_dkk": 283.58,
    "price_eur": 37.99,
    "created_at": "2025-09-16T11:00:06.000000Z",
    "updated_at": "2025-09-16T21:20:05.000000Z"
  },
  {
    "id": 73812,
    "hour_dk": "2025-09-17T16:00:00.000000Z",
    "hour_utc": "2025-09-17T14:00:00.000000Z",
    "price_zone": "DK2",
    "price_dkk": 528.94,
    "price_eur": 70.86,
    "created_at": "2025-09-16T11:00:06.000000Z",
    "updated_at": "2025-09-16T21:20:05.000000Z"
  },
  {
    "id": 73815,
    "hour_dk": "2025-09-17T17:00:00.000000Z",
    "hour_utc": "2025-09-17T15:00:00.000000Z",
    "price_zone": "DK2",
    "price_dkk": 778.33,
    "price_eur": 104.27,
    "created_at": "2025-09-16T11:00:06.000000Z",
    "updated_at": "2025-09-16T21:20:05.000000Z"
  },
  {
    "id": 73816,
    "hour_dk": "2025-09-17T18:00:00.000000Z",
    "hour_utc": "2025-09-17T16:00:00.000000Z",
    "price_zone": "DK2",
    "price_dkk": 875.15,
    "price_eur": 117.24,
    "created_at": "2025-09-16T11:00:06.000000Z",
    "updated_at": "2025-09-16T21:20:05.000000Z"
  },
  {
    "id": 73819,
    "hour_dk": "2025-09-17T19:00:00.000000Z",
    "hour_utc": "2025-09-17T17:00:00.000000Z",
    "price_zone": "DK2",
    "price_dkk": 976.52,
    "price_eur": 130.82,
    "created_at": "2025-09-16T11:00:06.000000Z",
    "updated_at": "2025-09-16T21:20:05.000000Z"
  },
  {
    "id": 73820,
    "hour_dk": "2025-09-17T20:00:00.000000Z",
    "hour_utc": "2025-09-17T18:00:00.000000Z",
    "price_zone": "DK2",
    "price_dkk": 890.9,
    "price_eur": 119.35,
    "created_at": "2025-09-16T11:00:06.000000Z",
    "updated_at": "2025-09-16T21:20:05.000000Z"
  },
  {
    "id": 73823,
    "hour_dk": "2025-09-17T21:00:00.000000Z",
    "hour_utc": "2025-09-17T19:00:00.000000Z",
    "price_zone": "DK2",
    "price_dkk": 677.86,
    "price_eur": 90.81,
    "created_at": "2025-09-16T11:00:06.000000Z",
    "updated_at": "2025-09-16T21:20:05.000000Z"
  },
  {
    "id": 73824,
    "hour_dk": "2025-09-17T22:00:00.000000Z",
    "hour_utc": "2025-09-17T20:00:00.000000Z",
    "price_zone": "DK2",
    "price_dkk": 568.65,
    "price_eur": 76.18,
    "created_at": "2025-09-16T11:00:06.000000Z",
    "updated_at": "2025-09-16T21:20:05.000000Z"
  },
  {
    "id": 73827,
    "hour_dk": "2025-09-17T23:00:00.000000Z",
    "hour_utc": "2025-09-17T21:00:00.000000Z",
    "price_zone": "DK2",
    "price_dkk": 447.28,
    "price_eur": 59.92,
    "created_at": "2025-09-16T11:00:07.000000Z",
    "updated_at": "2025-09-16T21:20:05.000000Z"
  }
]
