[
  {
    "id": 72149,
    "hour_dk": "2025-08-15T00:00:00.000000Z",
    "hour_utc": "2025-08-14T22:00:00.000000Z",
    "price_zone": "DK2",
    "price_dkk": 743.72,
    "price_eur": 99.66,
    "created_at": "2025-08-14T11:00:04.000000Z",
    "updated_at": "2025-08-14T21:20:06.000000Z"
  },
  {
    "id": 72150,
    "hour_dk": "2025-08-15T01:00:00.000000Z",
    "hour_utc": "2025-08-14T23:00:00.000000Z",
    "price_zone": "DK2",
    "price_dkk": 739.02,
    "price_eur": 99.03,
    "created_at": "2025-08-14T11:00:04.000000Z",
    "updated_at": "2025-08-14T21:20:06.000000Z"
  },
  {
    "id": 72153,
    "hour_dk": "2025-08-15T02:00:00.000000Z",
    "hour_utc": "2025-08-15T00:00:00.000000Z",
    "price_zone": "DK2",
    "price_dkk": 701.11,
    "price_eur": 93.95,
    "created_at": "2025-08-14T11:00:04.000000Z",
    "updated_at": "2025-08-14T21:20:06.000000Z"
  },
  {
    "id": 72154,
    "hour_dk": "2025-08-15T03:00:00.000000Z",
    "hour_utc": "2025-08-15T01:00:00.000000Z",
    "price_zone": "DK2",
    "price_dkk": 674.47,
    "price_eur": 90.38,
    "created_at": "2025-08-14T11:00:05.000000Z",
    "updated_at": "2025-08-14T21:20:06.000000Z"
  },
  {
    "id": 72157,
    "hour_dk": "2025-08-15T04:00:00.000000Z",
    "hour_utc": "2025-08-15T02:00:00.000000Z",
    "price_zone": "DK2",
    "price_dkk": 686.93,
    "price_eur": 92.05,
    "created_at": "2025-08-14T11:00:05.000000Z",
    "updated_at": "2025-08-14T21:20:06.000000Z"
  },
  {
    "id": 72158,
    "hour_dk": "2025-08-15T05:00:00.000000Z",
    "hour_utc": "2025-08-15T03:00:00.000000Z",
    "price_zone": "DK2",
    "price_dkk": 723.57,
    "price_eur": 96.96,
    "created_at": "2025-08-14T11:00:05.000000Z",
    "updated_at": "2025-08-14T21:20:06.000000Z"
  },
  {
    "id": 72161,
    "hour_dk": "2025-08-15T06:00:00.000000Z",
    "hour_utc": "2025-08-15T04:00:00.000000Z",
    "price_zone": "DK2",
    "price_dkk": 759.1,
    "price_eur": 101.72,
    "created_at": "2025-08-14T11:00:05.000000Z",
    "updated_at": "2025-08-14T21:20:06.000000Z"
  },
  {
    "id": 72162,
    "hour_dk": "2025-08-15T07:00:00.000000Z",
    "hour_utc": "2025-08-15T05:00:00.000000Z",
    "price_zone": "DK2",
    "price_dkk": 756.26,
    "price_eur": 101.34,
    "created_at": "2025-08-14T11:00:05.000000Z",
    "updated_at": "2025-08-14T21:20:06.000000Z"
  },
  {
    "id": 72165,
    "hour_dk": "2025-08-15T08:00:00.000000Z",
    "hour_utc": "2025-08-15T06:00:00.000000Z",
    "price_zone": "DK2",
    "price_dkk": 720.89,
    "price_eur": 96.6,
    "created_at": "2025-08-14T11:00:05.000000Z",
    "updated_at": "2025-08-14T21:20:06.000000Z"
  },
  {
    "id": 72166,
    "hour_dk": "2025-08-15T09:00:00.000000Z",
    "hour_utc": "2025-08-15T07:00:00.000000Z",
    "price_zone": "DK2",
    "price_dkk": 622.9,
    "price_eur": 83.47,
    "created_at": "2025-08-14T11:00:05.000000Z",
    "updated_at": "2025-08-14T21:20:06.000000Z"
  },
  {
    "id": 72169,
    "hour_dk": "2025-08-15T10:00:00.000000Z",
    "hour_utc": "2025-08-15T08:00:00.000000Z",
    "price_zone": "DK2",
    "price_dkk": 319.85,
    "price_eur": 42.86,
    "created_at": "2025-08-14T11:00:05.000000Z",
    "updated_at": "2025-08-14T21:20:06.000000Z"
  },
  {
    "id": 72170,
    "hour_dk": "2025-08-15T11:00:00.000000Z",
    "hour_utc": "2025-08-15T09:00:00.000000Z",
    "price_zone": "DK2",
    "price_dkk": 22.91,
    "price_eur": 3.07,
    "created_at": "2025-08-14T11:00:05.000000Z",
    "updated_at": "2025-08-14T21:20:06.000000Z"
  },
  {
    "id": 72173,
    "hour_dk": "2025-08-15T12:00:00.000000Z",
    "hour_utc": "2025-08-15T10:00:00.000000Z",
    "price_zone": "DK2",
    "price_dkk": 7.84,
    "price_eur": 1.05,
    "created_at": "2025-08-14T11:00:05.000000Z",
    "updated_at": "2025-08-14T21:20:06.000000Z"
  },
  {
    "id": 72174,
    "hour_dk": "2025-08-15T13:00:00.000000Z",
    "hour_utc": "2025-08-15T11:00:00.000000Z",
    "price_zone": "DK2",
    "price_dkk": 4.48,
    "price_eur": 0.6,
    "created_at": "2025-08-14T11:00:05.000000Z",
    "updated_at": "2025-08-14T21:20:06.000000Z"
  },
  {
    "id": 72177,
    "hour_dk": "2025-08-15T14:00:00.000000Z",
    "hour_utc": "2025-08-15T12:00:00.000000Z",
    "price_zone": "DK2",
    "price_dkk": 0.07,
    "price_eur": 0.01,
    "created_at": "2025-08-14T11:00:05.000000Z",
    "updated_at": "2025-08-14T21:20:06.000000Z"
  },
  {
    "id": 72178,
    "hour_dk": "2025-08-15T15:00:00.000000Z",
    "hour_utc": "2025-08-15T13:00:00.000000Z",
    "price_zone": "DK2",
    "price_dkk": 13.43,
    "price_eur": 1.8,
    "created_at": "2025-08-14T11:00:05.000000Z",
    "updated_at": "2025-08-14T21:20:06.000000Z"
  },
  {
    "id": 72181,
    "hour_dk": "2025-08-15T16:00:00.000000Z",
    "hour_utc": "2025-08-15T14:00:00.000000Z",
    "price_zone": "DK2",
    "price_dkk": 205.89,
    "price_eur": 27.59,
    "created_at": "2025-08-14T11:00:05.000000Z",
    "updated_at": "2025-08-14T21:20:07.000000Z"
  },
  {
    "id": 72182,
    "hour_dk": "2025-08-15T17:00:00.000000Z",
    "hour_utc": "2025-08-15T15:00:00.000000Z",
    "price_zone": "DK2",
    "price_dkk": 564.02,
    "price_eur": 75.58,
    "created_at": "2025-08-14T11:00:05.000000Z",
    "updated_at": "2025-08-14T21:20:07.000000Z"
  },
  {
    "id": 72185,
    "hour_dk": "2025-08-15T18:00:00.000000Z",
    "hour_utc": "2025-08-15T16:00:00.000000Z",
    "price_zone": "DK2",
    "price_dkk": 727.75,
    "price_eur": 97.52,
    "created_at": "2025-08-14T11:00:05.000000Z",
    "updated_at": "2025-08-14T21:20:07.000000Z"
  },
  {
    "id": 72186,
    "hour_dk": "2025-08-15T19:00:00.000000Z",
    "hour_utc": "2025-08-15T17:00:00.000000Z",
    "price_zone": "DK2",
    "price_dkk": 836.71,
    "price_eur": 112.12,
    "created_at": "2025-08-14T11:00:05.000000Z",
    "updated_at": "2025-08-14T21:20:07.000000Z"
  },
  {
    "id": 72189,
    "hour_dk": "2025-08-15T20:00:00.000000Z",
    "hour_utc": "2025-08-15T18:00:00.000000Z",
    "price_zone": "DK2",
    "price_dkk": 882.6,
    "price_eur": 118.27,
    "created_at": "2025-08-14T11:00:05.000000Z",
    "updated_at": "2025-08-14T21:20:07.000000Z"
  },
  {
    "id": 72190,
    "hour_dk": "2025-08-15T21:00:00.000000Z",
    "hour_utc": "2025-08-15T19:00:00.000000Z",
    "price_zone": "DK2",
    "price_dkk": 787.68,
    "price_eur": 105.55,
    "created_at": "2025-08-14T11:00:05.000000Z",
    "updated_at": "2025-08-14T21:20:07.000000Z"
  },
  {
    "id": 72193,
    "hour_dk": "2025-08-15T22:00:00.000000Z",
    "hour_utc": "2025-08-15T20:00:00.000000Z",
    "price_zone": "DK2",
    "price_dkk": 739.17,
    "price_eur": 99.05,
    "created_at": "2025-08-14T11:00:05.000000Z",
    "updated_at": "2025-08-14T21:20:07.000000Z"
  },
  {
    "id": 72194,
    "hour_dk": "2025-08-15T23:00:00.000000Z",
    "hour_utc": "2025-08-15T21:00:00.000000Z",
    "price_zone": "DK2",
    "price_dkk": 677.53,
    "price_eur": 90.79,
    "created_at": "2025-08-14T11:00:06.000000Z",
    "updated_at": "2025-08-14T21:20:07.000000Z"
  }
]
